jnc/__init__.py
jnc/py.typed
japanese_number_converter-1.0.1.dist-info/LICENSE
japanese_number_converter-1.0.1.dist-info/WHEEL
japanese_number_converter-1.0.1.dist-info/METADATA
japanese_number_converter-1.0.1.dist-info/RECORD
