Metadata-Version: 2.1
Name: japanese-number-converter
Version: 1.0.1
Summary: convert japanese numbers to arabic numbers
Home-page: https://github.com/kitagawa-hr/japanese-numbers-converter
License: MIT
Keywords: japanese,number,parser
Author: Haruki Kitagawa
Author-email: kitagawahr@gmail.com
Requires-Python: >=3.6,<4.0
Classifier: License :: OSI Approved :: MIT License
Classifier: Programming Language :: Python :: 3
Classifier: Programming Language :: Python :: 3.6
Classifier: Programming Language :: Python :: 3.7
Classifier: Programming Language :: Python :: 3.8
Classifier: Programming Language :: Python :: 3.9
Project-URL: Repository, https://github.com/kitagawa-hr/japanese-numbers-converter
